<odoo>
    <!-- Cost Sheet Report Template -->
    <template id="report_cost_sheet_document">
        <t t-call="web.html_container">
            <t t-foreach="docs" t-as="doc">
                <div class="page" style="font-family: Arial, sans-serif; font-size: 10pt; line-height: 1.3;">
                    <style>
                        .table-bordered {
                            border: 1px solid #ddd;
                        }
                        .table-bordered th, .table-bordered td {
                            border: 1px solid #ddd;
                            padding: 8px;
                        }
                        .section-title {
                            background-color: #f0f0f0;
                            padding: 5px;
                            margin-top: 15px;
                            margin-bottom: 10px;
                            font-weight: bold;
                        }
                    </style>
                    <h2 class="text-left mb-4">Cost Sheet: <t t-esc="doc.name"/></h2>
                    <p>Total Cost: <t t-esc="doc.total_cost"/></p>
                    <table class="table table-sm table-bordered">
                        <thead>
                            <tr>
                                <th>Work Center</th>
                                <th>Hours Spent</th>
                                <th>Subtotal</th>
                            </tr>
                        </thead>
                        <tbody>
                            <t t-foreach="doc.line_ids" t-as="line">
                                <tr>
                                    <td><t t-esc="line.work_center_id.name"/></td>
                                    <td><t t-esc="line.hours_spent"/></td>
                                    <td><t t-esc="line.subtotal"/></td>
                                </tr>
                            </t>
                        </tbody>
                    </table>
                    <div class="section-title">Description</div>
                    <p t-esc="doc.description"/>
                </div>
            </t>
        </t>
    </template>
</odoo>
